HEtools/__init__.py
HEtools/coefmod.py
HEtools-0.5.0.dist-info/METADATA
HEtools-0.5.0.dist-info/WHEEL
HEtools-0.5.0.dist-info/top_level.txt
HEtools-0.5.0.dist-info/RECORD
