Metadata-Version: 2.1
Name: HEtools
Version: 0.5.0
Author: Bastiaan Quast
Author-email: <bquast@gmail.com>
Keywords: homomorphic encryption,FHE,cryptography,coefmod,modulo,coefficient modulo,polynomial
Classifier: Development Status :: 3 - Alpha
Classifier: Intended Audience :: Education
Classifier: Programming Language :: Python :: 2
Classifier: Programming Language :: Python :: 3
Classifier: Operating System :: MacOS :: MacOS X
Classifier: Operating System :: Microsoft :: Windows
Requires-Dist: numpy
